enigmator/__init__.py
enigmator/src/__init__.py
enigmator/src/enigma.py
enigmator/src/plugboard.py
enigmator/src/reflector.py
enigmator/src/rotor.py
enigmator/tests/__init__.py
enigmator/tests/test_plugboard.py
enigmator/tests/test_reflector.py
enigmator/tests/test_rotor.py
enigmator/tests/test_whole_enigma.py
enigmator-1.0.4.dist-info/LICENSE
enigmator-1.0.4.dist-info/METADATA
enigmator-1.0.4.dist-info/WHEEL
enigmator-1.0.4.dist-info/top_level.txt
enigmator-1.0.4.dist-info/RECORD
