Metadata-Version: 2.1
Name: enigmator
Version: 1.0.4
Summary: Package for decrypting messages with an enigma machine
Home-page: https://github.com/gitstetter/enigma
Author: Andreas Fussstetter
Author-email: a.fussstetter@hotmail.com
License: MIT
Platform: UNKNOWN
Classifier: License :: OSI Approved :: MIT License
Classifier: Programming Language :: Python :: 3
Classifier: Operating System :: OS Independent
Classifier: Development Status :: 5 - Production/Stable
Requires-Python: >=3.7.7
License-File: LICENSE
Provides-Extra: dev
Requires-Dist: pytest (>=5.4.1) ; extra == 'dev'
Requires-Dist: twine (>=4.0.2) ; extra == 'dev'
